betterKickAPI/__init__.py
betterKickAPI/constants.py
betterKickAPI/helper.py
betterKickAPI/kick.py
betterKickAPI/oauth.py
betterKickAPI/py.typed
betterKickAPI/servers.py
betterKickAPI/types.py
betterKickAPI/eventsub/__init__.py
betterKickAPI/eventsub/base.py
betterKickAPI/eventsub/events.py
betterKickAPI/eventsub/utils.py
betterKickAPI/eventsub/webhook.py
betterKickAPI/object/__init__.py
betterKickAPI/object/api.py
betterKickAPI/object/base.py
betterKickAPI/object/eventsub.py
betterkickapi-1.0.1.dist-info/METADATA
betterkickapi-1.0.1.dist-info/WHEEL
betterkickapi-1.0.1.dist-info/licenses/LICENSE
betterkickapi-1.0.1.dist-info/RECORD
