Metadata-Version: 2.4
Name: betterKickAPI
Version: 1.0.1
Summary: A Python 3.9+ implementation of the Kick API and Webhook. Highly inspired on twitchAPI
Project-URL: Repository, https://github.com/Benjas333/pyKickAPI
Project-URL: Issues, https://github.com/Benjas333/pyKickAPI/issues
Project-URL: Changelog, https://github.com/Benjas333/pyKickAPI/blob/master/CHANGELOG.md
Author-email: Benjas333 <seston30@gmail.com>
License-Expression: MIT
License-File: LICENSE
Keywords: EventSub,api,chat,event sub,kick,kick.com,kickapi,webhook
Classifier: Development Status :: 5 - Production/Stable
Classifier: Intended Audience :: Developers
Classifier: Programming Language :: Python
Classifier: Programming Language :: Python :: 3
Classifier: Programming Language :: Python :: 3.9
Classifier: Programming Language :: Python :: 3.10
Classifier: Programming Language :: Python :: 3.11
Classifier: Programming Language :: Python :: 3.12
Classifier: Topic :: Communications
Classifier: Topic :: Software Development :: Libraries
Classifier: Topic :: Software Development :: Libraries :: Application Frameworks
Classifier: Topic :: Software Development :: Libraries :: Python Modules
Requires-Python: >=3.9
Requires-Dist: aiofiles>=25.1.0
Requires-Dist: aiohttp>=3.13.2
Requires-Dist: cryptography>=46.0.3
Requires-Dist: enum-tools>=0.13.0
Requires-Dist: orjson>=3.11.4
Requires-Dist: pydantic>=2.12.3
Requires-Dist: socketify>=0.0.31
Requires-Dist: strenum>=0.4.15
